dockerizeasml/__init__.py
dockerizeasml/dockerizer.py
dockerizeasml-0.2.8.dist-info/LICENSE
dockerizeasml-0.2.8.dist-info/METADATA
dockerizeasml-0.2.8.dist-info/WHEEL
dockerizeasml-0.2.8.dist-info/entry_points.txt
dockerizeasml-0.2.8.dist-info/top_level.txt
dockerizeasml-0.2.8.dist-info/RECORD
