Metadata-Version: 2.1
Name: dockerizeasml
Version: 0.2.8
Summary: A tool to dockerize machine learning projects
Author: Aviroop Pal
Author-email: avirooppal42@gmail.com
Classifier: Programming Language :: Python :: 3
Classifier: License :: OSI Approved :: MIT License
Classifier: Operating System :: OS Independent
Requires-Python: >=3.6
License-File: LICENSE
